README.md
ReadME_pypi.md
setup.py
EESMHM/AminoAcidConverter.py
EESMHM/CLI.py
EESMHM/__init__.py
EESMHM/energy_eval.py
EESMHM/input_parser.py
EESMHM/intercaatInterface.py
EESMHM/main.py
EESMHM/mutant_model.py
EESMHM.egg-info/PKG-INFO
EESMHM.egg-info/SOURCES.txt
EESMHM.egg-info/dependency_links.txt
EESMHM.egg-info/entry_points.txt
EESMHM.egg-info/requires.txt
EESMHM.egg-info/top_level.txt