Metadata-Version: 2.1
Name: EESMHM
Version: 1.0
Summary: Energy Evaluation of Single Mutant Homology Models
Home-page: https://github.com/eved1018/EESMHM
Author: Evan Edelstein
Author-email: edelsteinevan@gmail.com
License: MIT
Platform: UNKNOWN
